cipher_speck/__init__.py
cipher_speck/speck.py
speck_cipher-0.1.1.dist-info/METADATA
speck_cipher-0.1.1.dist-info/WHEEL
speck_cipher-0.1.1.dist-info/top_level.txt
speck_cipher-0.1.1.dist-info/RECORD
